openbb/__init__.py
openbb/assets/reference.json
openbb/package/__extensions__.py
openbb/package/commodity.py
openbb/package/commodity_price.py
openbb/package/crypto.py
openbb/package/crypto_price.py
openbb/package/currency.py
openbb/package/currency_price.py
openbb/package/derivatives.py
openbb/package/derivatives_futures.py
openbb/package/derivatives_options.py
openbb/package/economy.py
openbb/package/economy_gdp.py
openbb/package/economy_survey.py
openbb/package/equity.py
openbb/package/equity_calendar.py
openbb/package/equity_compare.py
openbb/package/equity_discovery.py
openbb/package/equity_estimates.py
openbb/package/equity_fundamental.py
openbb/package/equity_ownership.py
openbb/package/equity_price.py
openbb/package/equity_shorts.py
openbb/package/etf.py
openbb/package/fixedincome.py
openbb/package/fixedincome_corporate.py
openbb/package/fixedincome_government.py
openbb/package/fixedincome_rate.py
openbb/package/fixedincome_spreads.py
openbb/package/index.py
openbb/package/index_price.py
openbb/package/news.py
openbb/package/regulators.py
openbb/package/regulators_cftc.py
openbb/package/regulators_sec.py
openbb/py.typed
openbb-4.4.4.dist-info/METADATA
openbb-4.4.4.dist-info/WHEEL
openbb-4.4.4.dist-info/RECORD
