Metadata-Version: 2.3
Name: openbb
Version: 4.4.4
Summary: Investment research for everyone, anywhere.
License: AGPL-3.0-only
Author: OpenBB Team
Author-email: hello@openbb.co
Requires-Python: >=3.9.21,<3.13
Classifier: License :: OSI Approved :: GNU Affero General Public License v3
Classifier: Programming Language :: Python :: 3
Classifier: Programming Language :: Python :: 3.10
Classifier: Programming Language :: Python :: 3.11
Classifier: Programming Language :: Python :: 3.12
Provides-Extra: all
Provides-Extra: alpha-vantage
Provides-Extra: biztoc
Provides-Extra: cboe
Provides-Extra: charting
Provides-Extra: ecb
Provides-Extra: econometrics
Provides-Extra: finra
Provides-Extra: finviz
Provides-Extra: government-us
Provides-Extra: multpl
Provides-Extra: nasdaq
Provides-Extra: quantitative
Provides-Extra: seeking-alpha
Provides-Extra: stockgrid
Provides-Extra: technical
Provides-Extra: tmx
Provides-Extra: tradier
Provides-Extra: wsj
Requires-Dist: openbb-alpha-vantage (>=1.4.1,<2.0.0) ; extra == "alpha-vantage" or extra == "all"
Requires-Dist: openbb-benzinga (>=1.4.1,<2.0.0)
Requires-Dist: openbb-biztoc (>=1.4.2,<2.0.0) ; extra == "biztoc" or extra == "all"
Requires-Dist: openbb-bls (>=1.1.2,<2.0.0)
Requires-Dist: openbb-cboe (>=1.4.1,<2.0.0) ; extra == "cboe" or extra == "all"
Requires-Dist: openbb-cftc (>=1.1.1,<2.0.0)
Requires-Dist: openbb-charting (>=2.3.4,<3.0.0) ; extra == "charting" or extra == "all"
Requires-Dist: openbb-commodity (>=1.3.1,<2.0.0)
Requires-Dist: openbb-core (>=1.4.6,<2.0.0)
Requires-Dist: openbb-crypto (>=1.4.1,<2.0.0)
Requires-Dist: openbb-currency (>=1.4.1,<2.0.0)
Requires-Dist: openbb-deribit (>=1.0.1,<2.0.0) ; extra == "all"
Requires-Dist: openbb-derivatives (>=1.4.1,<2.0.0)
Requires-Dist: openbb-ecb (>=1.4.2,<2.0.0) ; extra == "ecb" or extra == "all"
Requires-Dist: openbb-econdb (>=1.3.1,<2.0.0)
Requires-Dist: openbb-econometrics (>=1.5.3,<2.0.0) ; extra == "econometrics" or extra == "all"
Requires-Dist: openbb-economy (>=1.4.2,<2.0.0)
Requires-Dist: openbb-equity (>=1.4.1,<2.0.0)
Requires-Dist: openbb-etf (>=1.4.1,<2.0.0)
Requires-Dist: openbb-federal-reserve (>=1.4.2,<2.0.0)
Requires-Dist: openbb-finra (>=1.4.1,<2.0.0) ; extra == "finra" or extra == "all"
Requires-Dist: openbb-finviz (>=1.3.1,<2.0.0) ; extra == "finviz" or extra == "all"
Requires-Dist: openbb-fixedincome (>=1.4.3,<2.0.0)
Requires-Dist: openbb-fmp (>=1.4.2,<2.0.0)
Requires-Dist: openbb-fred (>=1.4.4,<2.0.0)
Requires-Dist: openbb-government-us (>=1.4.1,<2.0.0) ; extra == "government-us" or extra == "all"
Requires-Dist: openbb-imf (>=1.1.1,<2.0.0)
Requires-Dist: openbb-index (>=1.4.1,<2.0.0)
Requires-Dist: openbb-intrinio (>=1.4.1,<2.0.0)
Requires-Dist: openbb-multpl (>=1.1.1,<2.0.0) ; extra == "multpl" or extra == "all"
Requires-Dist: openbb-nasdaq (>=1.4.1,<2.0.0) ; extra == "nasdaq" or extra == "all"
Requires-Dist: openbb-news (>=1.4.1,<2.0.0)
Requires-Dist: openbb-oecd (>=1.4.1,<2.0.0)
Requires-Dist: openbb-platform-api (>=1.1.6,<2.0.0)
Requires-Dist: openbb-polygon (>=1.4.1,<2.0.0)
Requires-Dist: openbb-quantitative (>=1.4.3,<2.0.0) ; extra == "quantitative" or extra == "all"
Requires-Dist: openbb-regulators (>=1.4.2,<2.0.0)
Requires-Dist: openbb-sec (>=1.4.3,<2.0.0)
Requires-Dist: openbb-seeking-alpha (>=1.4.1,<2.0.0) ; extra == "seeking-alpha" or extra == "all"
Requires-Dist: openbb-stockgrid (>=1.4.1,<2.0.0) ; extra == "stockgrid" or extra == "all"
Requires-Dist: openbb-technical (>=1.4.3,<2.0.0) ; extra == "technical" or extra == "all"
Requires-Dist: openbb-tiingo (>=1.4.1,<2.0.0)
Requires-Dist: openbb-tmx (>=1.3.2,<2.0.0) ; extra == "tmx" or extra == "all"
Requires-Dist: openbb-tradier (>=1.3.1,<2.0.0) ; extra == "tradier" or extra == "all"
Requires-Dist: openbb-tradingeconomics (>=1.4.1,<2.0.0)
Requires-Dist: openbb-us-eia (>=1.1.1,<2.0.0)
Requires-Dist: openbb-wsj (>=1.4.1,<2.0.0) ; extra == "wsj" or extra == "all"
Requires-Dist: openbb-yfinance (>=1.4.3,<2.0.0)
